<DanmakuGraph Name="SukebanShotFire">

    <Velocity Set="2"/>

    <Projectile Name="MiniBullet" ShotInfoUseType="Add" DirectionType="AITarget"/>
    <Wait Time="0.1"/>
    <Angle Set="Random_-5^5"/>
    <Projectile Name="MiniBullet" ShotInfoUseType="Add" DirectionType="AITarget"/>
    <Wait Time="0.1"/>
    <Angle Set="Random_-5^5"/>
    <Projectile Name="MiniBullet" ShotInfoUseType="Add" DirectionType="AITarget"/>
    <Wait Time="0.1"/>
    <Angle Set="Random_-5^5"/>
    <Projectile Name="MiniBullet" ShotInfoUseType="Add" DirectionType="AITarget"/>
    <Wait Time="0.1"/>
    <Angle Set="Random_-5^5"/>
    <Projectile Name="MiniBullet" ShotInfoUseType="Add" DirectionType="AITarget"/>

</DanmakuGraph>